{
  "key": "https://api.postcodes.io/postcodes/ST7%208LQ",
  "url": "https://api.postcodes.io/postcodes/ST7%208LQ",
  "retrievedAt": "2026-07-03T12:44:09.647Z",
  "body": {
    "status": 200,
    "result": {
      "postcode": "ST7 8LQ",
      "quality": 1,
      "eastings": 380403,
      "northings": 349961,
      "country": "England",
      "nhs_ha": "West Midlands",
      "longitude": -2.293769,
      "latitude": 53.046567,
      "european_electoral_region": "West Midlands",
      "primary_care_trust": "North Staffordshire",
      "region": "West Midlands",
      "lsoa": "Newcastle-under-Lyme 005E",
      "msoa": "Newcastle-under-Lyme 005",
      "incode": "8LQ",
      "outcode": "ST7",
      "parliamentary_constituency": "Newcastle-under-Lyme",
      "parliamentary_constituency_2024": "Newcastle-under-Lyme",
      "senedd_constituency": null,
      "senedd_constituency_no": null,
      "admin_district": "Newcastle-under-Lyme",
      "parish": "Audley Rural",
      "admin_county": "Staffordshire",
      "date_of_introduction": "198001",
      "date_of_termination": null,
      "index_of_multiple_deprivation": 18409,
      "admin_ward": "Audley",
      "ced": "Audley & Chesterton",
      "ccg": "NHS Staffordshire and Stoke-on-Trent",
      "nuts": "Newcastle-under-Lyme",
      "pfa": "Staffordshire",
      "nhs_region": "Midlands",
      "ttwa": "Stoke-on-Trent",
      "national_park": "England (non-National Park)",
      "bua": "Miles Green",
      "icb": "NHS Staffordshire and Stoke-on-Trent Integrated Care Board",
      "cancer_alliance": "West Midlands",
      "lsoa11": "Newcastle-under-Lyme 005E",
      "msoa11": "Newcastle-under-Lyme 005",
      "lsoa21": "Newcastle-under-Lyme 005E",
      "msoa21": "Newcastle-under-Lyme 005",
      "oa21": "E00150606",
      "ruc11": "(England/Wales) Rural town and fringe",
      "ruc21": "Smaller rural: Nearer to a major town or city",
      "lep1": "Stoke-on-Trent and Staffordshire",
      "lep2": null,
      "codes": {
        "admin_district": "E07000195",
        "admin_county": "E10000028",
        "admin_ward": "E05011415",
        "parish": "E04008943",
        "parliamentary_constituency": "E14001380",
        "parliamentary_constituency_2024": "E14001380",
        "ccg": "E38000126",
        "ccg_id": "05G",
        "ced": "E58001796",
        "nuts": "TLG24",
        "lsoa": "E01029556",
        "msoa": "E02006162",
        "lau2": "E07000195",
        "pfa": "E23000015",
        "nhs_region": "E40000011",
        "ttwa": "E30000273",
        "national_park": "E65000001",
        "bua": "E63008980",
        "icb": "E54000010",
        "cancer_alliance": "E56000007",
        "lsoa11": "E01029556",
        "msoa11": "E02006162",
        "lsoa21": "E01029556",
        "msoa21": "E02006162",
        "oa21": "E00150606",
        "ruc11": "D1",
        "ruc21": "RSN1",
        "lep1": "E37000032",
        "lep2": null
      }
    }
  }
}
